memeoverflow/__init__.py
memeoverflow/db.py
memeoverflow/exc.py
memeoverflow/memeoverflow.py
memeoverflow/stackexchange.py
memeoverflow/twitter.py
memeoverflow/utils.py
memeoverflow/imgflip/__init__.py
memeoverflow/imgflip/memes.py
memeoverflow-0.8.0.dist-info/LICENSE.md
memeoverflow-0.8.0.dist-info/METADATA
memeoverflow-0.8.0.dist-info/WHEEL
memeoverflow-0.8.0.dist-info/top_level.txt
memeoverflow-0.8.0.dist-info/RECORD
