Metadata-Version: 2.1
Name: memeoverflow
Version: 0.8.0
Summary: Simple framework for Twitter bots creating memes from Stack Exchange questions
Home-page: https://github.com/bennuttall/meme-overflow
Author: Ben Nuttall
Author-email: ben@bennuttall.com
License: BSD 3-Clause License
Project-URL: Source Code, https://github.com/bennuttall/meme-overflow
Project-URL: Issue Tracker, https://github.com/bennuttall/meme-overflow/issues
Keywords: twitter,stackoverflow,stackexchange,meme,imgflip
Platform: UNKNOWN
Classifier: Development Status :: 4 - Beta
Classifier: License :: OSI Approved :: BSD License
Classifier: Topic :: Games/Entertainment
Classifier: Programming Language :: Python :: 3
Classifier: Programming Language :: Python :: 3 :: Only
Classifier: Programming Language :: Python :: 3.6
Classifier: Programming Language :: Python :: 3.7
Classifier: Programming Language :: Python :: 3.8
Classifier: Programming Language :: Python :: 3.9
Requires-Python: >=3.6
Requires-Dist: setuptools
Requires-Dist: requests
Requires-Dist: twython
Requires-Dist: logzero
Provides-Extra: test
Requires-Dist: pytest ; extra == 'test'
Requires-Dist: coverage ; extra == 'test'
Requires-Dist: mock ; extra == 'test'
Requires-Dist: pylint ; extra == 'test'
